{
  "data": {
    "article": {},
    "attachments": {},
    "author_id": "1809604484173295620",
    "conversation_id": "2061100874337050827",
    "created_at": "2026-05-31T15:35:11.000Z",
    "edit_controls": {
      "editable_until": "2026-05-31T16:35:11.000Z",
      "edits_remaining": 5,
      "is_edit_eligible": false
    },
    "edit_history_tweet_ids": [
      "2061109242426487239"
    ],
    "entities": {
      "mentions": [
        {
          "end": 12,
          "id": "1887196654547443714",
          "start": 0,
          "username": "asuka613321"
        }
      ]
    },
    "geo": {},
    "id": "2061109242426487239",
    "in_reply_to_user_id": "1887196654547443714",
    "lang": "zh",
    "note_tweet": {
      "entities": {}
    },
    "possibly_sensitive": false,
    "public_metrics": {
      "bookmark_count": 0,
      "impression_count": 0,
      "like_count": 0,
      "quote_count": 0,
      "reply_count": 0,
      "retweet_count": 0
    },
    "referenced_tweets": [
      {
        "id": "2061109054697836788",
        "type": "replied_to"
      }
    ],
    "reply_settings": "everyone",
    "text": "@asuka613321 可以的，如果没人来我会去找找，符合要求的我就把他赞赏码啥的推你吧"
  },
  "includes": {
    "tweets": [
      {
        "article": {},
        "attachments": {},
        "author_id": "1809604484173295620",
        "conversation_id": "2061100874337050827",
        "created_at": "2026-05-31T15:35:11.000Z",
        "edit_controls": {
          "editable_until": "2026-05-31T16:35:11.000Z",
          "edits_remaining": 5,
          "is_edit_eligible": false
        },
        "edit_history_tweet_ids": [
          "2061109242426487239"
        ],
        "entities": {
          "mentions": [
            {
              "end": 12,
              "id": "1887196654547443714",
              "start": 0,
              "username": "asuka613321"
            }
          ]
        },
        "geo": {},
        "id": "2061109242426487239",
        "in_reply_to_user_id": "1887196654547443714",
        "lang": "zh",
        "note_tweet": {
          "entities": {}
        },
        "possibly_sensitive": false,
        "public_metrics": {
          "bookmark_count": 0,
          "impression_count": 0,
          "like_count": 0,
          "quote_count": 0,
          "reply_count": 0,
          "retweet_count": 0
        },
        "referenced_tweets": [
          {
            "id": "2061109054697836788",
            "type": "replied_to"
          }
        ],
        "reply_settings": "everyone",
        "text": "@asuka613321 可以的，如果没人来我会去找找，符合要求的我就把他赞赏码啥的推你吧"
      },
      {
        "article": {},
        "attachments": {},
        "author_id": "1887196654547443714",
        "conversation_id": "2061100874337050827",
        "created_at": "2026-05-31T15:34:26.000Z",
        "edit_controls": {
          "editable_until": "2026-05-31T16:34:26.000Z",
          "edits_remaining": 5,
          "is_edit_eligible": false
        },
        "edit_history_tweet_ids": [
          "2061109054697836788"
        ],
        "entities": {
          "mentions": [
            {
              "end": 10,
              "id": "1809604484173295620",
              "start": 0,
              "username": "for_4ngel"
            }
          ]
        },
        "geo": {},
        "id": "2061109054697836788",
        "in_reply_to_user_id": "1809604484173295620",
        "lang": "zh",
        "note_tweet": {
          "entities": {}
        },
        "possibly_sensitive": false,
        "public_metrics": {
          "bookmark_count": 0,
          "impression_count": 4,
          "like_count": 0,
          "quote_count": 0,
          "reply_count": 1,
          "retweet_count": 0
        },
        "referenced_tweets": [
          {
            "id": "2061100874337050827",
            "type": "replied_to"
          }
        ],
        "reply_settings": "everyone",
        "text": "@for_4ngel 哥，如果碰到真的需要帮助的可以tt我，我再加50"
      }
    ],
    "users": [
      {
        "created_at": "2024-07-06T15:05:18.000Z",
        "description": "07  |♂ | 双相情感障碍C-PTSD BPD-E  | 自残 | OD | 学过一些人格学，心理学以及药理学 最擅长的是依恋人格学和人格障碍学还有一些od相关的药理学，有问题可以来找我可以把我当情绪垃圾桶，非常乐意解答希望你们都好好的Angel永远在这里🤪，欢迎互fo",
        "id": "1809604484173295620",
        "location": "若能成為誰的心臟",
        "name": "Angel",
        "pinned_tweet_id": "2060574328085995870",
        "profile_image_url": "https://pbs.twimg.com/profile_images/2058112788934098944/ke7b7Se3_normal.jpg",
        "protected": false,
        "public_metrics": {
          "followers_count": 193,
          "following_count": 405,
          "like_count": 208,
          "listed_count": 0,
          "media_count": 17,
          "tweet_count": 325
        },
        "username": "for_4ngel",
        "verified": false
      },
      {
        "created_at": "2025-02-05T17:49:04.000Z",
        "description": "",
        "id": "1887196654547443714",
        "name": "asuka7",
        "profile_image_url": "https://pbs.twimg.com/profile_images/1887196832058781696/XIq7_-as_normal.jpg",
        "protected": false,
        "public_metrics": {
          "followers_count": 6,
          "following_count": 162,
          "like_count": 113,
          "listed_count": 0,
          "media_count": 1,
          "tweet_count": 19
        },
        "username": "asuka613321",
        "verified": false
      }
    ]
  }
}