{
  "data": {
    "article": {},
    "attachments": {},
    "author_id": "1809604484173295620",
    "conversation_id": "2060733699470356647",
    "created_at": "2026-05-30T15:38:29.000Z",
    "edit_controls": {
      "editable_until": "2026-05-30T16:38:29.000Z",
      "edits_remaining": 5,
      "is_edit_eligible": false
    },
    "edit_history_tweet_ids": [
      "2060747683342717052"
    ],
    "entities": {
      "mentions": [
        {
          "end": 13,
          "id": "1854207757123207168",
          "start": 0,
          "username": "duo_shu62376"
        }
      ]
    },
    "geo": {},
    "id": "2060747683342717052",
    "in_reply_to_user_id": "1854207757123207168",
    "lang": "zh",
    "note_tweet": {
      "entities": {}
    },
    "possibly_sensitive": false,
    "public_metrics": {
      "bookmark_count": 0,
      "impression_count": 0,
      "like_count": 0,
      "quote_count": 0,
      "reply_count": 0,
      "retweet_count": 0
    },
    "referenced_tweets": [
      {
        "id": "2060747284137037961",
        "type": "replied_to"
      }
    ],
    "reply_settings": "everyone",
    "text": "@duo_shu62376 dm简述一下你的情况我看看需不需要"
  },
  "includes": {
    "tweets": [
      {
        "article": {},
        "attachments": {},
        "author_id": "1809604484173295620",
        "conversation_id": "2060733699470356647",
        "created_at": "2026-05-30T15:38:29.000Z",
        "edit_controls": {
          "editable_until": "2026-05-30T16:38:29.000Z",
          "edits_remaining": 5,
          "is_edit_eligible": false
        },
        "edit_history_tweet_ids": [
          "2060747683342717052"
        ],
        "entities": {
          "mentions": [
            {
              "end": 13,
              "id": "1854207757123207168",
              "start": 0,
              "username": "duo_shu62376"
            }
          ]
        },
        "geo": {},
        "id": "2060747683342717052",
        "in_reply_to_user_id": "1854207757123207168",
        "lang": "zh",
        "note_tweet": {
          "entities": {}
        },
        "possibly_sensitive": false,
        "public_metrics": {
          "bookmark_count": 0,
          "impression_count": 0,
          "like_count": 0,
          "quote_count": 0,
          "reply_count": 0,
          "retweet_count": 0
        },
        "referenced_tweets": [
          {
            "id": "2060747284137037961",
            "type": "replied_to"
          }
        ],
        "reply_settings": "everyone",
        "text": "@duo_shu62376 dm简述一下你的情况我看看需不需要"
      },
      {
        "article": {},
        "attachments": {},
        "author_id": "1854207757123207168",
        "conversation_id": "2060733699470356647",
        "created_at": "2026-05-30T15:36:54.000Z",
        "edit_controls": {
          "editable_until": "2026-05-30T16:36:54.000Z",
          "edits_remaining": 5,
          "is_edit_eligible": false
        },
        "edit_history_tweet_ids": [
          "2060747284137037961"
        ],
        "entities": {
          "mentions": [
            {
              "end": 10,
              "id": "1809604484173295620",
              "start": 0,
              "username": "for_4ngel"
            }
          ]
        },
        "geo": {},
        "id": "2060747284137037961",
        "in_reply_to_user_id": "1809604484173295620",
        "lang": "zh",
        "note_tweet": {
          "entities": {}
        },
        "possibly_sensitive": false,
        "public_metrics": {
          "bookmark_count": 0,
          "impression_count": 2,
          "like_count": 0,
          "quote_count": 0,
          "reply_count": 1,
          "retweet_count": 0
        },
        "referenced_tweets": [
          {
            "id": "2060733699470356647",
            "type": "replied_to"
          }
        ],
        "reply_settings": "everyone",
        "text": "@for_4ngel 可以试一下吗 谢谢你。"
      }
    ],
    "users": [
      {
        "created_at": "2024-07-06T15:05:18.000Z",
        "description": "07  |♂ | 双相情感障碍C-PTSD BPD-E  | 自残 | OD | 学过一些人格学，心理学以及药理学 最擅长的是依恋人格学和人格障碍学还有一些od相关的药理学，有问题可以来找我可以把我当情绪垃圾桶，非常乐意解答希望你们都好好的Angel永远在这里🤪，欢迎互fo",
        "id": "1809604484173295620",
        "location": "天堂",
        "name": "Angel",
        "pinned_tweet_id": "2060574328085995870",
        "profile_image_url": "https://pbs.twimg.com/profile_images/2058112788934098944/ke7b7Se3_normal.jpg",
        "protected": false,
        "public_metrics": {
          "followers_count": 116,
          "following_count": 396,
          "like_count": 161,
          "listed_count": 0,
          "media_count": 16,
          "tweet_count": 278
        },
        "username": "for_4ngel",
        "verified": false
      },
      {
        "created_at": "2024-11-06T17:02:50.000Z",
        "description": "04/oder/双相asd/家里蹲/\n可以叫我我鼠多多\n反差m 配合度高 屁股大 冷白皮 bbw 纯正大母猪\n🚪188/288/520\n qq201526684\n（谨慎关注我）",
        "id": "1854207757123207168",
        "name": "食堂子优选打菜大妈",
        "pinned_tweet_id": "2035259585033118155",
        "profile_image_url": "https://pbs.twimg.com/profile_images/1854208185709793280/LXs3cMlO_normal.jpg",
        "protected": false,
        "public_metrics": {
          "followers_count": 90,
          "following_count": 83,
          "like_count": 193,
          "listed_count": 2,
          "media_count": 80,
          "tweet_count": 506
        },
        "username": "duo_shu62376",
        "verified": false
      }
    ]
  }
}