{
  "data": {
    "article": {},
    "attachments": {},
    "author_id": "1809604484173295620",
    "conversation_id": "2060549907380113680",
    "created_at": "2026-05-30T10:03:47.000Z",
    "edit_controls": {
      "editable_until": "2026-05-30T11:03:47.000Z",
      "edits_remaining": 5,
      "is_edit_eligible": false
    },
    "edit_history_tweet_ids": [
      "2060663453694771364"
    ],
    "entities": {
      "mentions": [
        {
          "end": 11,
          "id": "1752259037566218240",
          "start": 0,
          "username": "aru_ve_lut"
        }
      ]
    },
    "geo": {},
    "id": "2060663453694771364",
    "in_reply_to_user_id": "1752259037566218240",
    "lang": "zh",
    "note_tweet": {
      "entities": {}
    },
    "possibly_sensitive": false,
    "public_metrics": {
      "bookmark_count": 0,
      "impression_count": 0,
      "like_count": 0,
      "quote_count": 0,
      "reply_count": 0,
      "retweet_count": 0
    },
    "referenced_tweets": [
      {
        "id": "2060549907380113680",
        "type": "replied_to"
      }
    ],
    "reply_settings": "everyone",
    "text": "@aru_ve_lut 内源解离不舒服的，有躯体化症状过的都体验过吧，很麻木空洞的感觉"
  },
  "includes": {
    "tweets": [
      {
        "article": {},
        "attachments": {},
        "author_id": "1809604484173295620",
        "conversation_id": "2060549907380113680",
        "created_at": "2026-05-30T10:03:47.000Z",
        "edit_controls": {
          "editable_until": "2026-05-30T11:03:47.000Z",
          "edits_remaining": 5,
          "is_edit_eligible": false
        },
        "edit_history_tweet_ids": [
          "2060663453694771364"
        ],
        "entities": {
          "mentions": [
            {
              "end": 11,
              "id": "1752259037566218240",
              "start": 0,
              "username": "aru_ve_lut"
            }
          ]
        },
        "geo": {},
        "id": "2060663453694771364",
        "in_reply_to_user_id": "1752259037566218240",
        "lang": "zh",
        "note_tweet": {
          "entities": {}
        },
        "possibly_sensitive": false,
        "public_metrics": {
          "bookmark_count": 0,
          "impression_count": 0,
          "like_count": 0,
          "quote_count": 0,
          "reply_count": 0,
          "retweet_count": 0
        },
        "referenced_tweets": [
          {
            "id": "2060549907380113680",
            "type": "replied_to"
          }
        ],
        "reply_settings": "everyone",
        "text": "@aru_ve_lut 内源解离不舒服的，有躯体化症状过的都体验过吧，很麻木空洞的感觉"
      },
      {
        "article": {},
        "attachments": {},
        "author_id": "1752259037566218240",
        "conversation_id": "2060549907380113680",
        "created_at": "2026-05-30T02:32:35.000Z",
        "edit_controls": {
          "editable_until": "2026-05-30T03:32:35.000Z",
          "edits_remaining": 5,
          "is_edit_eligible": true
        },
        "edit_history_tweet_ids": [
          "2060549907380113680"
        ],
        "entities": {},
        "geo": {},
        "id": "2060549907380113680",
        "lang": "zh",
        "note_tweet": {
          "entities": {}
        },
        "possibly_sensitive": false,
        "public_metrics": {
          "bookmark_count": 0,
          "impression_count": 284,
          "like_count": 11,
          "quote_count": 0,
          "reply_count": 5,
          "retweet_count": 0
        },
        "reply_settings": "everyone",
        "text": "羡慕那些能自己解离的，不用吃愈美片"
      }
    ],
    "users": [
      {
        "created_at": "2024-07-06T15:05:18.000Z",
        "description": "07  |♂ | 双相情感障碍C-PTSD BPD-E  | 自残 | OD | 学过一些人格学，心理学以及药理学 最擅长的是依恋人格学和人格障碍学还有一些od相关的药理学，有问题可以来找我可以把我当情绪垃圾桶，非常乐意解答希望你们都好好的Angel永远在这里🤪，欢迎互fo",
        "id": "1809604484173295620",
        "location": "天堂",
        "name": "Angel",
        "pinned_tweet_id": "2059007335809589317",
        "profile_image_url": "https://pbs.twimg.com/profile_images/2058112788934098944/ke7b7Se3_normal.jpg",
        "protected": false,
        "public_metrics": {
          "followers_count": 108,
          "following_count": 392,
          "like_count": 159,
          "listed_count": 0,
          "media_count": 15,
          "tweet_count": 260
        },
        "username": "for_4ngel",
        "verified": false
      },
      {
        "created_at": "2024-01-30T09:14:57.000Z",
        "description": "atto/见晴miharu/081013/日常推/中文/En/日语学习中/intp-a/od/自残/休学/友跨/希望和大家交朋友/超级社恐/很温良的小女孩/欢迎互fo 直fo就是喜欢你",
        "id": "1752259037566218240",
        "name": "见晴",
        "profile_image_url": "https://pbs.twimg.com/profile_images/2045456632256290816/rzugZvz8_normal.jpg",
        "protected": false,
        "public_metrics": {
          "followers_count": 192,
          "following_count": 353,
          "like_count": 1206,
          "listed_count": 0,
          "media_count": 64,
          "tweet_count": 382
        },
        "username": "aru_ve_lut",
        "verified": false
      }
    ]
  }
}